{
    "$schema": "https://json-schema.org/draft/2020-12/schema",
    "$id": "https://raw.githubusercontent.com/blues/notecard-schema/master/card.binary.rsp.notecard.api.json",
    "title": "card.binary Response Application Programming Interface (API) Schema",
    "type": "object",
    "properties": {
        "cobs": {
            "description": "The size of COBS-encoded data stored in the reserved area",
            "type": "integer"
        },
        "connected": {
            "description": "Returns true if the Notecard is connected to the network",
            "type": "boolean"
        },
        "err": {
            "description": "If present, a string describing the error that occurred during transmission",
            "type": "string"
        },
        "length": {
            "description": "The length of the binary data",
            "type": "integer"
        }
    },
    "version": "0.1.1",
    "apiVersion": "9.1.1"
}
